django_rijkshuisstijl-0.3.1.dist-info/licenses/LICENSE
rijkshuisstijl/__init__.py
rijkshuisstijl/conf/__init__.py
rijkshuisstijl/conf/settings.py
rijkshuisstijl/js/index.js
rijkshuisstijl/js/components/index.js
rijkshuisstijl/js/components/button/constants.js
rijkshuisstijl/js/components/button/index.js
rijkshuisstijl/js/components/datagrid/constants.js
rijkshuisstijl/js/components/datagrid/datagrid-edit.js
rijkshuisstijl/js/components/datagrid/datagrid-export.js
rijkshuisstijl/js/components/datagrid/datagrid-filter.js
rijkshuisstijl/js/components/datagrid/index.js
rijkshuisstijl/js/components/fake-link/constants.js
rijkshuisstijl/js/components/fake-link/fake-link.js
rijkshuisstijl/js/components/fake-link/index.js
rijkshuisstijl/js/components/filter/constants.js
rijkshuisstijl/js/components/filter/filter.js
rijkshuisstijl/js/components/filter/index.js
rijkshuisstijl/js/components/form/constants.js
rijkshuisstijl/js/components/form/date-input.js
rijkshuisstijl/js/components/form/form-control.js
rijkshuisstijl/js/components/form/form.js
rijkshuisstijl/js/components/form/index.js
rijkshuisstijl/js/components/form/input-filepicker.js
rijkshuisstijl/js/components/form/link-select.js
rijkshuisstijl/js/components/form/select.js
rijkshuisstijl/js/components/form/time-input.js
rijkshuisstijl/js/components/paginator/constants.js
rijkshuisstijl/js/components/paginator/index.js
rijkshuisstijl/js/components/paginator/paginator.js
rijkshuisstijl/js/components/search/constants.js
rijkshuisstijl/js/components/search/index.js
rijkshuisstijl/js/components/search/search.js
rijkshuisstijl/js/components/sticky-detect/constants.js
rijkshuisstijl/js/components/sticky-detect/index.js
rijkshuisstijl/js/components/sticky-detect/sticky-navigation-bar.js
rijkshuisstijl/js/components/summary/constants.js
rijkshuisstijl/js/components/summary/index.js
rijkshuisstijl/js/components/summary/summary.js
rijkshuisstijl/js/components/tabs/constants.js
rijkshuisstijl/js/components/tabs/index.js
rijkshuisstijl/js/components/tabs/tabs.js
django_rijkshuisstijl-0.3.1.dist-info/METADATA
django_rijkshuisstijl-0.3.1.dist-info/WHEEL
django_rijkshuisstijl-0.3.1.dist-info/top_level.txt
django_rijkshuisstijl-0.3.1.dist-info/RECORD
