Metadata-Version: 2.4
Name: django-rijkshuisstijl
Version: 0.3.1
Summary: Rijkshuisstijl boilerplate for Django.
Home-page: https://github.com/maykinmedia/django-rijkshuisstijl
Author: Maykin Media
Author-email: support@maykinmedia.nl
License: MIT
Keywords: Rijkshuisstijl
Classifier: Development Status :: 3 - Alpha
Classifier: Framework :: Django
Classifier: Framework :: Django :: 4.2
Classifier: Framework :: Django :: 5.2
Classifier: Intended Audience :: Developers
Classifier: Operating System :: Unix
Classifier: Operating System :: MacOS
Classifier: Operating System :: Microsoft :: Windows
Classifier: Programming Language :: Python
Classifier: Topic :: Software Development :: Libraries :: Python Modules
License-File: LICENSE
Requires-Dist: beautifulsoup4
Requires-Dist: django>=4.2
Requires-Dist: django-sitetree
Provides-Extra: tests
Requires-Dist: pytest; extra == "tests"
Requires-Dist: pytest-django; extra == "tests"
Requires-Dist: tox; extra == "tests"
Requires-Dist: isort; extra == "tests"
Provides-Extra: pep8
Requires-Dist: flake8; extra == "pep8"
Provides-Extra: coverage
Requires-Dist: pytest-cov; extra == "coverage"
Provides-Extra: docs
Requires-Dist: sphinx; extra == "docs"
Requires-Dist: sphinx-rtd-theme; extra == "docs"
Provides-Extra: release
Requires-Dist: bump-my-version; extra == "release"
Dynamic: license-file
